Dynamic_Nelson_Siegel_Svensson_Kalman_Filter/Kfilter.py
Dynamic_Nelson_Siegel_Svensson_Kalman_Filter/__init__.py
Dynamic_Nelson_Siegel_Svensson_Kalman_Filter/factor_loadings.py
Dynamic_Nelson_Siegel_Svensson_Kalman_Filter/kalman.py
Dynamic_Nelson_Siegel_Svensson_Kalman_Filter/lyapunov.py
Dynamic_Nelson_Siegel_Svensson_Kalman_Filter-0.1.0.dist-info/LICENSE.txt
Dynamic_Nelson_Siegel_Svensson_Kalman_Filter-0.1.0.dist-info/METADATA
Dynamic_Nelson_Siegel_Svensson_Kalman_Filter-0.1.0.dist-info/WHEEL
Dynamic_Nelson_Siegel_Svensson_Kalman_Filter-0.1.0.dist-info/entry_points.txt
Dynamic_Nelson_Siegel_Svensson_Kalman_Filter-0.1.0.dist-info/top_level.txt
Dynamic_Nelson_Siegel_Svensson_Kalman_Filter-0.1.0.dist-info/RECORD
