Metadata-Version: 2.1
Name: Dynamic-Nelson-Siegel-Svensson-Kalman-Filter
Version: 0.1.0
Summary: Implementation of the Dynamic-Nelson-Siegel-Svensson models with Kalman FilterFitting and Forecasting the Yield Curve.
Home-page: https://github.com/werleycordeiro/Dynamic_Nelson_Siegel_Svensson_Kalman_Filter
Author: Werley Cordeiro
Author-email: werleycordeiro@gmail.com
License: MIT license
Download-URL: https://github.com/werleycordeiro/Dynamic_Nelson_Siegel_Svensson_Kalman_Filter/archive/v_0.1.0.tar.gz
Keywords: Dynamic_Nelson_Siegel_Svensson_Kalman_Filter
Platform: UNKNOWN
Classifier: Programming Language :: Python :: 3
Classifier: Intended Audience :: Developers
Classifier: License :: OSI Approved :: MIT License
Classifier: Operating System :: OS Independent
Requires-Dist: pandas (>=0.23)
Requires-Dist: numpy (>=1.14)
